KNN/__init__.py
KNN/assessment/__init__.py
KNN/assessment/cross_validation.py
KNN/assessment/model_metrics.py
KNN/modelling/KNN_data_collection.py
KNN/modelling/__init__.py
KNN/modelling/generate_predictions.py
ubc_knn-0.11.dist-info/METADATA
ubc_knn-0.11.dist-info/WHEEL
ubc_knn-0.11.dist-info/top_level.txt
ubc_knn-0.11.dist-info/RECORD
